{
  "@context": [
    "https://w3id.org/ro/crate/1.2/context",
    {
      "bia": "https://bioimage-archive.org/ro-crate/",
      "obo": "http://purl.obolibrary.org/obo/",
      "dwc": "http://rs.tdwg.org/dwc/terms/",
      "dwciri": "http://rs.tdwg.org/dwc/iri/",
      "bao": "http://www.bioassayontology.org/bao#",
      "vernacularName": {
        "@id": "dwc:vernacularName"
      },
      "scientificName": {
        "@id": "dwc:scientificName"
      },
      "hasCellLine": {
        "@id": "bao:BAO_0002004"
      },
      "measurementMethod": {
        "@id": "dwciri:measurementMethod"
      },
      "seeAlso": {
        "@id": "rdf:seeAlso"
      },
      "BioSample": {
        "@id": "http://schema.org/BioSample"
      },
      "LabProtocol": {
        "@id": "http://schema.org/LabProtocol"
      },
      "labEquipment": {
        "@id": "http://schema.org/labEquipment"
      }
    }
  ],
  "@graph": [
    {
      "@id": "S-BSST841-ro-crate-metadata.json",
      "@type": [
        "CreativeWork"
      ],
      "conformsTo": {
        "@id": "https://w3id.org/ro/crate/1.2"
      },
      "about": [
        {
          "@id": "https://www.ebi.ac.uk/biostudies/bioimages/studies/S-BSST841"
        }
      ]
    },
    {
      "@id": "https://www.ebi.ac.uk/biostudies/bioimages/studies/S-BSST841",
      "@type": [
        "Dataset"
      ],
      "measurementMethod": [],
      "about": [],
      "author": [
        {
          "@id": "#fb2c4c95-7d42-4483-9792-c87040d27392"
        }
      ],
      "citation": [],
      "datePublished": "2022-05-15",
      "description": "Trabecular meshwork cell CRISPR knockout screen of genes at loci associated with intraocular pressure (IOP) in order to identify genetic regulators of IOP that may contribute to the pathogenesis of primary open angle glaucoma.",
      "funder": [],
      "identifier": "S-BSST841",
      "keywords": [],
      "license": "https://creativecommons.org/publicdomain/zero/1.0/",
      "name": "Trabecular meshwork cell CRISPR knockout screen",
      "publisher": {
        "@id": "https://www.ebi.ac.uk/bioimage-archive/"
      },
      "size": [
        {
          "@id": "#480bb0bc-db43-46e5-88ae-071380b9d63c"
        },
        {
          "@id": "#1037e7dd-b10a-47a1-885c-1f3b2998ff1c"
        }
      ],
      "thumbnailUrl": []
    },
    {
      "@id": "#fb2c4c95-7d42-4483-9792-c87040d27392",
      "@type": [
        "Person"
      ],
      "affiliation": [
        {
          "@id": "#03e494ba-ee75-41f9-b417-c9e39e860b04"
        }
      ],
      "email": "connor.greatbatch@utas.edu.au",
      "name": "Connor Greabatch"
    },
    {
      "@id": "#03e494ba-ee75-41f9-b417-c9e39e860b04",
      "@type": [
        "Organization"
      ],
      "name": "University of Tasmania"
    },
    {
      "@id": "https://www.ebi.ac.uk/bioimage-archive/",
      "@type": [
        "Organization"
      ],
      "name": "BioImage Archive"
    },
    {
      "@id": "#1037e7dd-b10a-47a1-885c-1f3b2998ff1c",
      "@type": [
        "QuantitiveValue"
      ],
      "unitCode": "http://purl.obolibrary.org/obo/UO_0000189",
      "unitText": "file count",
      "value": 2
    },
    {
      "@id": "#480bb0bc-db43-46e5-88ae-071380b9d63c",
      "@type": [
        "QuantitiveValue"
      ],
      "unitCode": "http://purl.obolibrary.org/obo/UO_0000233",
      "unitText": "bytes",
      "value": 44983232385
    }
  ]
}